[
  {
    "rank": 1,
    "name": "Oumaïma ALLASSAK",
    "country": "",
    "points": 259.2
  },
  {
    "rank": 2,
    "name": "Sofija HINIC",
    "country": "",
    "points": 247.3
  },
  {
    "rank": 3,
    "name": "VIOLETA DIAZ ARRIBAS",
    "country": "",
    "points": 171.44
  },
  {
    "rank": 4,
    "name": "Anastasiia VOLOSENKO",
    "country": "",
    "points": 145.18
  },
  {
    "rank": 5,
    "name": "Nicole MASALA",
    "country": "",
    "points": 112.16
  },
  {
    "rank": 6,
    "name": "Deya PEEVA",
    "country": "",
    "points": 87.07
  },
  {
    "rank": 7,
    "name": "OLGA DESYLLA",
    "country": "",
    "points": 80.94
  },
  {
    "rank": 8,
    "name": "Anja RADEVIC",
    "country": "",
    "points": 75.84
  },
  {
    "rank": 9,
    "name": "Dora RADEK",
    "country": "",
    "points": 74.86
  },
  {
    "rank": 10,
    "name": "Vasiliki PAPADOPOULOU",
    "country": "",
    "points": 70.8
  },
  {
    "rank": 11,
    "name": "Dina KAMANDI",
    "country": "",
    "points": 65.75
  },
  {
    "rank": 12,
    "name": "Ejla MAKAS",
    "country": "",
    "points": 63.4
  },
  {
    "rank": 13,
    "name": "Lara TUŠKAN",
    "country": "",
    "points": 59.4
  },
  {
    "rank": 14,
    "name": "KYRIAKI EIRINI ILIADI",
    "country": "",
    "points": 58.76
  },
  {
    "rank": 15,
    "name": "Kasija NESOVIC",
    "country": "",
    "points": 48
  },
  {
    "rank": 16,
    "name": "MULKIYE ECE ULUSOY",
    "country": "",
    "points": 47.76
  },
  {
    "rank": 17,
    "name": "V IKTORIA VARGA",
    "country": "",
    "points": 47.52
  },
  {
    "rank": 18,
    "name": "EVANGELIA ZARKADA",
    "country": "",
    "points": 46.8
  },
  {
    "rank": 19,
    "name": "Monica PETRUT",
    "country": "",
    "points": 45.95
  },
  {
    "rank": 20,
    "name": "Humay DADASHOVA",
    "country": "",
    "points": 37.82
  },
  {
    "rank": 21,
    "name": "Barbara STRZEMKOWSKA",
    "country": "",
    "points": 36.25
  },
  {
    "rank": 22,
    "name": "Inari SUSILUOTO",
    "country": "",
    "points": 35.88
  },
  {
    "rank": 23,
    "name": "Andriana IOANNOU",
    "country": "",
    "points": 34.01
  },
  {
    "rank": 24,
    "name": "Tara SLJIVANCANIN",
    "country": "",
    "points": 33.02
  },
  {
    "rank": 25,
    "name": "Amela NUTI",
    "country": "",
    "points": 32.7
  },
  {
    "rank": 26,
    "name": "Leire LOPEZ RAMIREZ",
    "country": "",
    "points": 32.22
  },
  {
    "rank": 27,
    "name": "Natália ZAGYIOVÁ",
    "country": "",
    "points": 31.78
  },
  {
    "rank": 28,
    "name": "Raya IVANOVA",
    "country": "",
    "points": 30
  },
  {
    "rank": 29,
    "name": "Gabriela WRZESZCZ",
    "country": "",
    "points": 25.92
  },
  {
    "rank": 30,
    "name": "Jázmin SCHRENK",
    "country": "",
    "points": 25.79
  },
  {
    "rank": 31,
    "name": "Alyssa LIU",
    "country": "",
    "points": 25.76
  },
  {
    "rank": 32,
    "name": "Elina KRUMOVA",
    "country": "",
    "points": 23.5
  },
  {
    "rank": 33,
    "name": "Deniz UNAL",
    "country": "",
    "points": 23.29
  },
  {
    "rank": 34,
    "name": "Aina KIRTSELIS",
    "country": "",
    "points": 20.3
  },
  {
    "rank": 35,
    "name": "Nika DODIK",
    "country": "",
    "points": 20
  },
  {
    "rank": 36,
    "name": "Milica VASIC",
    "country": "",
    "points": 19.68
  },
  {
    "rank": 37,
    "name": "Zoë LEMMENS",
    "country": "",
    "points": 19.14
  },
  {
    "rank": 38,
    "name": "Vera PSHONKA",
    "country": "",
    "points": 18.97
  },
  {
    "rank": 39,
    "name": "Fenne STEENAERTS",
    "country": "",
    "points": 18.36
  },
  {
    "rank": 40,
    "name": "Leyla OZKAN",
    "country": "",
    "points": 18.24
  },
  {
    "rank": 41,
    "name": "Ozum SALMA",
    "country": "",
    "points": 18
  },
  {
    "rank": 42,
    "name": "Venelina YANKOVA",
    "country": "",
    "points": 17.28
  },
  {
    "rank": 42,
    "name": "Adela FAFULOVIC",
    "country": "",
    "points": 17.28
  },
  {
    "rank": 42,
    "name": "Pirzanat CHOPALAEVA",
    "country": "",
    "points": 17.28
  },
  {
    "rank": 45,
    "name": "Masa NESIC",
    "country": "",
    "points": 16.62
  },
  {
    "rank": 46,
    "name": "Lihi CHMILEVSKY",
    "country": "",
    "points": 16.27
  },
  {
    "rank": 47,
    "name": "CHRYSOULA KOGKOULERI",
    "country": "",
    "points": 16.2
  },
  {
    "rank": 48,
    "name": "Sadio CAUMONT",
    "country": "",
    "points": 16
  },
  {
    "rank": 49,
    "name": "Nazaah WALIULLAH",
    "country": "",
    "points": 15.36
  },
  {
    "rank": 50,
    "name": "Roza Theofania TSOUTSIKA",
    "country": "",
    "points": 14.4
  },
  {
    "rank": 50,
    "name": "Yaryna KOSTIUK",
    "country": "",
    "points": 14.4
  },
  {
    "rank": 52,
    "name": "Carolina GODINHO",
    "country": "",
    "points": 12.7
  },
  {
    "rank": 53,
    "name": "ENRIETA BERBERI",
    "country": "",
    "points": 11.88
  },
  {
    "rank": 54,
    "name": "Teodora MARINOVA",
    "country": "",
    "points": 11.7
  },
  {
    "rank": 55,
    "name": "Fatma Zehra AKYAZICI",
    "country": "",
    "points": 11.52
  },
  {
    "rank": 56,
    "name": "Sevval Ela ALPASLAN",
    "country": "",
    "points": 10.44
  },
  {
    "rank": 57,
    "name": "Amelie CLAES",
    "country": "",
    "points": 10.32
  },
  {
    "rank": 58,
    "name": "JUDITH CORDOBA HEREDIA",
    "country": "",
    "points": 10.2
  },
  {
    "rank": 59,
    "name": "Lana JAKARA",
    "country": "",
    "points": 10.08
  },
  {
    "rank": 60,
    "name": "Sigrid JOHNSSON",
    "country": "",
    "points": 10.02
  },
  {
    "rank": 61,
    "name": "FU-HSUAN LIU",
    "country": "",
    "points": 10
  },
  {
    "rank": 61,
    "name": "Xenia MAÑALICH GARCIA",
    "country": "",
    "points": 10
  },
  {
    "rank": 61,
    "name": "KYRIAKI KARAGKIOZAKI",
    "country": "",
    "points": 10
  },
  {
    "rank": 61,
    "name": "Alannis Michelle ALERS ROMAN",
    "country": "",
    "points": 10
  },
  {
    "rank": 61,
    "name": "Chieh-Ling WANG",
    "country": "",
    "points": 10
  },
  {
    "rank": 61,
    "name": "Emma KELC",
    "country": "",
    "points": 10
  },
  {
    "rank": 67,
    "name": "PETRA JERKOVIĆ",
    "country": "",
    "points": 9.72
  },
  {
    "rank": 67,
    "name": "Durda PETROVIC",
    "country": "",
    "points": 9.72
  },
  {
    "rank": 69,
    "name": "CANSU SOZEN",
    "country": "",
    "points": 9.59
  },
  {
    "rank": 70,
    "name": "Gema GALVEZ CAIRON",
    "country": "",
    "points": 9
  },
  {
    "rank": 71,
    "name": "Kamilla SOLTAMOVA",
    "country": "",
    "points": 8.89
  },
  {
    "rank": 72,
    "name": "Khatia GAROZASHVILI",
    "country": "",
    "points": 8.47
  },
  {
    "rank": 73,
    "name": "DINA GIMENEZ",
    "country": "",
    "points": 8.15
  },
  {
    "rank": 74,
    "name": "Greta RÜCKER",
    "country": "",
    "points": 7.92
  },
  {
    "rank": 74,
    "name": "Stella KOLB",
    "country": "",
    "points": 7.92
  },
  {
    "rank": 76,
    "name": "CEMRE AKTAS",
    "country": "",
    "points": 7.67
  },
  {
    "rank": 77,
    "name": "Alina LUBASEVA",
    "country": "",
    "points": 7.56
  },
  {
    "rank": 78,
    "name": "CHRISTINA DANAI KAKARETSA",
    "country": "",
    "points": 7.2
  },
  {
    "rank": 78,
    "name": "Hena MELEZ",
    "country": "",
    "points": 7.2
  },
  {
    "rank": 80,
    "name": "ZEYNEP TEKIN",
    "country": "",
    "points": 6.91
  },
  {
    "rank": 81,
    "name": "Sanna EKMAN",
    "country": "",
    "points": 6.8
  },
  {
    "rank": 82,
    "name": "Ludovica FUGAZZA",
    "country": "",
    "points": 6.48
  },
  {
    "rank": 82,
    "name": "Teodora KRSTIC",
    "country": "",
    "points": 6.48
  },
  {
    "rank": 84,
    "name": "Solomii SAVCHUK",
    "country": "",
    "points": 6.35
  },
  {
    "rank": 85,
    "name": "Hanna GALECKA",
    "country": "",
    "points": 6.3
  },
  {
    "rank": 86,
    "name": "Adele DEL VECCHIO",
    "country": "",
    "points": 6
  },
  {
    "rank": 86,
    "name": "Oihane FERNANDEZ LOPEZ",
    "country": "",
    "points": 6
  },
  {
    "rank": 86,
    "name": "Grace SIWEK",
    "country": "",
    "points": 6
  },
  {
    "rank": 89,
    "name": "Elpiniki ARGYRIOU",
    "country": "",
    "points": 5.94
  },
  {
    "rank": 90,
    "name": "Fiona SCHULZ",
    "country": "",
    "points": 5.76
  },
  {
    "rank": 90,
    "name": "Skye TAYLOR",
    "country": "",
    "points": 5.76
  },
  {
    "rank": 90,
    "name": "Noa MATEO PELAEZ",
    "country": "",
    "points": 5.76
  },
  {
    "rank": 93,
    "name": "IREM ATSIZ",
    "country": "",
    "points": 5.4
  },
  {
    "rank": 94,
    "name": "DAMLA RABIA SIMSEK",
    "country": "",
    "points": 5.29
  },
  {
    "rank": 95,
    "name": "ALEXANDRA MELKONIAN",
    "country": "",
    "points": 5
  },
  {
    "rank": 96,
    "name": "Seyidkhanim MAMMADOVA",
    "country": "",
    "points": 4.76
  },
  {
    "rank": 97,
    "name": "Laura KUJACIC",
    "country": "",
    "points": 4.54
  },
  {
    "rank": 97,
    "name": "Elpida SAPLAOURA",
    "country": "",
    "points": 4.54
  },
  {
    "rank": 97,
    "name": "ELEFTHERIA KALITSI",
    "country": "",
    "points": 4.54
  },
  {
    "rank": 97,
    "name": "DEFNE TANRIVERDI",
    "country": "",
    "points": 4.54
  },
  {
    "rank": 97,
    "name": "Melina GONZALEZ RAYO",
    "country": "",
    "points": 4.54
  },
  {
    "rank": 97,
    "name": "Rumeysa Derin Su TURE",
    "country": "",
    "points": 4.54
  },
  {
    "rank": 103,
    "name": "Rihanna Gabriela PETTERSSON",
    "country": "",
    "points": 4.5
  },
  {
    "rank": 104,
    "name": "BERFIN DONMEZ",
    "country": "",
    "points": 4.32
  },
  {
    "rank": 104,
    "name": "Solomiia SAVCHUK",
    "country": "",
    "points": 4.32
  },
  {
    "rank": 104,
    "name": "FERYEL KANDOUSSI",
    "country": "",
    "points": 4.32
  },
  {
    "rank": 104,
    "name": "Ebony BURTON",
    "country": "",
    "points": 4.32
  },
  {
    "rank": 104,
    "name": "Gulu ZAMANLI",
    "country": "",
    "points": 4.32
  },
  {
    "rank": 104,
    "name": "SIMA YONAK",
    "country": "",
    "points": 4.32
  },
  {
    "rank": 104,
    "name": "Yaren ERDEM",
    "country": "",
    "points": 4.32
  },
  {
    "rank": 104,
    "name": "INBAR BIN-NUN",
    "country": "",
    "points": 4.32
  },
  {
    "rank": 112,
    "name": "CHRISTINA GIOUVANOUDI",
    "country": "",
    "points": 3.6
  },
  {
    "rank": 112,
    "name": "ANASTASIA PETSI",
    "country": "",
    "points": 3.6
  },
  {
    "rank": 112,
    "name": "Seoyeon LEE",
    "country": "",
    "points": 3.6
  },
  {
    "rank": 112,
    "name": "Iara FIDALGO",
    "country": "",
    "points": 3.6
  },
  {
    "rank": 112,
    "name": "Andrea Sofia BALLARIN",
    "country": "",
    "points": 3.6
  },
  {
    "rank": 112,
    "name": "Nawel HIRTZ",
    "country": "",
    "points": 3.6
  },
  {
    "rank": 112,
    "name": "Dalia HODZIC",
    "country": "",
    "points": 3.6
  },
  {
    "rank": 119,
    "name": "Elizaveta ENACHE",
    "country": "",
    "points": 3.24
  },
  {
    "rank": 119,
    "name": "GIZEM GURCI",
    "country": "",
    "points": 3.24
  },
  {
    "rank": 119,
    "name": "Jana ABDALLAH",
    "country": "",
    "points": 3.24
  },
  {
    "rank": 119,
    "name": "SEVVAL SARICICEK",
    "country": "",
    "points": 3.24
  },
  {
    "rank": 119,
    "name": "Maria DINCOVA",
    "country": "",
    "points": 3.24
  },
  {
    "rank": 119,
    "name": "Nina DZUNIC",
    "country": "",
    "points": 3.24
  },
  {
    "rank": 125,
    "name": "Belinay GUNEL",
    "country": "",
    "points": 3.02
  },
  {
    "rank": 125,
    "name": "ZEYNEP NAZ GUR",
    "country": "",
    "points": 3.02
  },
  {
    "rank": 125,
    "name": "Riana KUMAKHOVA",
    "country": "",
    "points": 3.02
  },
  {
    "rank": 125,
    "name": "Esila BALTURK",
    "country": "",
    "points": 3.02
  },
  {
    "rank": 125,
    "name": "ZEYNEP KOCAMAN",
    "country": "",
    "points": 3.02
  },
  {
    "rank": 125,
    "name": "ELIF TUANA SATI",
    "country": "",
    "points": 3.02
  },
  {
    "rank": 125,
    "name": "Natalia IWANIUK",
    "country": "",
    "points": 3.02
  },
  {
    "rank": 125,
    "name": "ELSA HERBER",
    "country": "",
    "points": 3.02
  },
  {
    "rank": 125,
    "name": "Adriana AVENDAÑO HERNANDEZ",
    "country": "",
    "points": 3.02
  },
  {
    "rank": 134,
    "name": "Hadz MOMINA",
    "country": "",
    "points": 3
  },
  {
    "rank": 135,
    "name": "Lisea BRUNET",
    "country": "",
    "points": 2.88
  },
  {
    "rank": 136,
    "name": "Mariia SKOCHELIAS",
    "country": "",
    "points": 2.7
  },
  {
    "rank": 136,
    "name": "Ariana DORBOLO",
    "country": "",
    "points": 2.7
  },
  {
    "rank": 138,
    "name": "BERRA ERIS",
    "country": "",
    "points": 2.27
  },
  {
    "rank": 138,
    "name": "Natasza WOSKOWIAK",
    "country": "",
    "points": 2.27
  },
  {
    "rank": 138,
    "name": "ZEHRA KARAPINAR",
    "country": "",
    "points": 2.27
  },
  {
    "rank": 138,
    "name": "Merve UYSAL",
    "country": "",
    "points": 2.27
  },
  {
    "rank": 138,
    "name": "Zehra YILDIRIM",
    "country": "",
    "points": 2.27
  },
  {
    "rank": 138,
    "name": "EMINE KARACUKA",
    "country": "",
    "points": 2.27
  },
  {
    "rank": 138,
    "name": "TUANA KOLUKISAOGLU",
    "country": "",
    "points": 2.27
  },
  {
    "rank": 138,
    "name": "ECENUR SEVEN",
    "country": "",
    "points": 2.27
  },
  {
    "rank": 138,
    "name": "Ula JARULYTE",
    "country": "",
    "points": 2.27
  },
  {
    "rank": 138,
    "name": "DILBER SARGUL",
    "country": "",
    "points": 2.27
  },
  {
    "rank": 138,
    "name": "CENNET ELIF AKKULAK",
    "country": "",
    "points": 2.27
  },
  {
    "rank": 138,
    "name": "RONYA DILSA CELIK",
    "country": "",
    "points": 2.27
  },
  {
    "rank": 138,
    "name": "SILA ORUM",
    "country": "",
    "points": 2.27
  },
  {
    "rank": 151,
    "name": "DESPOINA NALMPANTI",
    "country": "",
    "points": 2.16
  },
  {
    "rank": 151,
    "name": "Rueya ERDEM",
    "country": "",
    "points": 2.16
  },
  {
    "rank": 151,
    "name": "Alaitz ANTON GONZALEZ",
    "country": "",
    "points": 2.16
  },
  {
    "rank": 151,
    "name": "EVANGELIA GIANNOPOULOU",
    "country": "",
    "points": 2.16
  },
  {
    "rank": 151,
    "name": "Borislava PETKOVA",
    "country": "",
    "points": 2.16
  },
  {
    "rank": 151,
    "name": "Ylenia BAÑOS ARNEDO",
    "country": "",
    "points": 2.16
  },
  {
    "rank": 151,
    "name": "TANIA AVILA SOLDEVILA",
    "country": "",
    "points": 2.16
  },
  {
    "rank": 151,
    "name": "Emma KAHLHOFER",
    "country": "",
    "points": 2.16
  },
  {
    "rank": 159,
    "name": "ELA SU DURMAZ",
    "country": "",
    "points": 2.12
  },
  {
    "rank": 159,
    "name": "Hacer Damre CALISKAN",
    "country": "",
    "points": 2.12
  },
  {
    "rank": 159,
    "name": "NISA NURAY YETGIN",
    "country": "",
    "points": 2.12
  },
  {
    "rank": 159,
    "name": "Gulay ALIYEVA",
    "country": "",
    "points": 2.12
  },
  {
    "rank": 163,
    "name": "Leire ECHANIZ CLAVER",
    "country": "",
    "points": 1.8
  },
  {
    "rank": 163,
    "name": "Alicia ALONSO",
    "country": "",
    "points": 1.8
  },
  {
    "rank": 165,
    "name": "Ayana GABIT",
    "country": "",
    "points": 1.62
  },
  {
    "rank": 165,
    "name": "Alina NAROZHNIAK",
    "country": "",
    "points": 1.62
  },
  {
    "rank": 165,
    "name": "ADA HERMELO RODRIGUEZ",
    "country": "",
    "points": 1.62
  },
  {
    "rank": 168,
    "name": "Alicia KACOU-FLEURY",
    "country": "",
    "points": 1.51
  },
  {
    "rank": 168,
    "name": "Safia BOUASSA",
    "country": "",
    "points": 1.51
  },
  {
    "rank": 168,
    "name": "Neda CHAFEHI CHANNAKI",
    "country": "",
    "points": 1.51
  },
  {
    "rank": 168,
    "name": "Mari Luz ÑIGUEZ RODRIGUEZ",
    "country": "",
    "points": 1.51
  },
  {
    "rank": 168,
    "name": "Carmen BALBOA PUJOL",
    "country": "",
    "points": 1.51
  },
  {
    "rank": 168,
    "name": "Noa GARCÍA GONZÁLEZ",
    "country": "",
    "points": 1.51
  },
  {
    "rank": 174,
    "name": "Safia Sevda ASKAROVA",
    "country": "",
    "points": 1.13
  },
  {
    "rank": 174,
    "name": "Andrea RAMOS REYES",
    "country": "",
    "points": 1.13
  },
  {
    "rank": 174,
    "name": "Ainara MORENO ESCOBAR",
    "country": "",
    "points": 1.13
  },
  {
    "rank": 177,
    "name": "Sabina KASYMOVA",
    "country": "",
    "points": 1.06
  }
]