[
  {
    "rank": 1,
    "name": "Lamprini Anna Asimaki",
    "country": "GRE",
    "points": 395.01
  },
  {
    "rank": 2,
    "name": "Lucija Kalic",
    "country": "CRO",
    "points": 275.92
  },
  {
    "rank": 3,
    "name": "Tina Ninic",
    "country": "SRB",
    "points": 264.06
  },
  {
    "rank": 4,
    "name": "Ludovica Fugazza",
    "country": "ITA",
    "points": 168.98
  },
  {
    "rank": 5,
    "name": "Zlatoslava Volosenko",
    "country": "UKR",
    "points": 147.21
  },
  {
    "rank": 6,
    "name": "Lucrezia Maloberti",
    "country": "ITA",
    "points": 94.87
  },
  {
    "rank": 7,
    "name": "Kasija Nesovic",
    "country": "SRB",
    "points": 90.0
  },
  {
    "rank": 8,
    "name": "Barbara Strzemkowska",
    "country": "POL",
    "points": 88.61
  },
  {
    "rank": 9,
    "name": "Alia Hasanovic",
    "country": "AUT",
    "points": 70.35
  },
  {
    "rank": 10,
    "name": "Nina Dzunic",
    "country": "SRB",
    "points": 66.29
  },
  {
    "rank": 11,
    "name": "Natália Zagyiová",
    "country": "SVK",
    "points": 64.31
  },
  {
    "rank": 12,
    "name": "Loïs Vanwesemael",
    "country": "BEL",
    "points": 61.15
  },
  {
    "rank": 13,
    "name": "Sofiia Shalokha",
    "country": "UKR",
    "points": 60.0
  },
  {
    "rank": 14,
    "name": "Lara Tuškan",
    "country": "CRO",
    "points": 58.82
  },
  {
    "rank": 15,
    "name": "🇪🇸",
    "country": "ESP",
    "points": 57.89
  },
  {
    "rank": 16,
    "name": "Nilufar Borji",
    "country": "AZE",
    "points": 57.22
  },
  {
    "rank": 17,
    "name": "Giulia Papoff",
    "country": "ITA",
    "points": 51.6
  },
  {
    "rank": 18,
    "name": "Matylda Szymczak",
    "country": "POL",
    "points": 50.5
  },
  {
    "rank": 19,
    "name": "Olja Bulatovic",
    "country": "SLO",
    "points": 46.97
  },
  {
    "rank": 20,
    "name": "Ioanna Konstantinou",
    "country": "CYP",
    "points": 45.91
  },
  {
    "rank": 21,
    "name": "Oumaïma Allassak",
    "country": "FRA",
    "points": 45.0
  },
  {
    "rank": 22,
    "name": "Gabriela Wrzeszcz",
    "country": "POL",
    "points": 43.6
  },
  {
    "rank": 23,
    "name": "Laura Kujacic",
    "country": "BIH",
    "points": 40.82
  },
  {
    "rank": 24,
    "name": "Noelia Bartoli",
    "country": "ITA",
    "points": 38.16
  },
  {
    "rank": 25,
    "name": "Lorena Loria",
    "country": "ITA",
    "points": 36.8
  },
  {
    "rank": 26,
    "name": "Arven Arzum Tuglu",
    "country": "TUR",
    "points": 36.72
  },
  {
    "rank": 27,
    "name": "Ebony Burton",
    "country": "GBR",
    "points": 36.25
  },
  {
    "rank": 28,
    "name": "Fatma Zehra Akyazici",
    "country": "TUR",
    "points": 36.24
  },
  {
    "rank": 29,
    "name": "Paulina Kovačević",
    "country": "CRO",
    "points": 35.35
  },
  {
    "rank": 30,
    "name": "Nawel Hirtz",
    "country": "FRA",
    "points": 35.27
  },
  {
    "rank": 31,
    "name": "Jovie Ho",
    "country": "GBR",
    "points": 34.46
  },
  {
    "rank": 32,
    "name": "Andriana Ioannou",
    "country": "CYP",
    "points": 32.04
  },
  {
    "rank": 33,
    "name": "Dimitra Marina Androni",
    "country": "GRE",
    "points": 30.96
  },
  {
    "rank": 34,
    "name": "Ela Karakaya",
    "country": "TUR",
    "points": 30.0
  },
  {
    "rank": 35,
    "name": "Evangelia Zarkada",
    "country": "SRB",
    "points": 29.8
  },
  {
    "rank": 36,
    "name": "Amani El Fatih",
    "country": "FRA",
    "points": 28.08
  },
  {
    "rank": 37,
    "name": "Arina Goncharova",
    "country": "RUS",
    "points": 28.08
  },
  {
    "rank": 38,
    "name": "Christina Anna Pepona",
    "country": "GRE",
    "points": 27.44
  },
  {
    "rank": 39,
    "name": "Vera Pshonka",
    "country": "BLR",
    "points": 27.17
  },
  {
    "rank": 40,
    "name": "Mariya Stoeva",
    "country": "BUL",
    "points": 27.02
  },
  {
    "rank": 41,
    "name": "Veronika Szentgyörgyi",
    "country": "HUN",
    "points": 26.76
  },
  {
    "rank": 42,
    "name": "Amelie Claes",
    "country": "BEL",
    "points": 25.37
  },
  {
    "rank": 43,
    "name": "Tereza Urbankova",
    "country": "CZE",
    "points": 24.63
  },
  {
    "rank": 44,
    "name": "Lana Graovac",
    "country": "CRO",
    "points": 24.44
  },
  {
    "rank": 45,
    "name": "Emma Kahlhofer",
    "country": "GER",
    "points": 24.32
  },
  {
    "rank": 46,
    "name": "Marie Zilz",
    "country": "GER",
    "points": 23.51
  },
  {
    "rank": 47,
    "name": "Chrysoula Kogkouleri",
    "country": "GRE",
    "points": 23.11
  },
  {
    "rank": 48,
    "name": "Mia Szita",
    "country": "CRO",
    "points": 22.73
  },
  {
    "rank": 49,
    "name": "Hena Melez",
    "country": "BIH",
    "points": 22.57
  },
  {
    "rank": 50,
    "name": "Ayse Elif Kunt",
    "country": "TUR",
    "points": 22.47
  },
  {
    "rank": 51,
    "name": "Rebecca Giordano",
    "country": "ITA",
    "points": 22.02
  },
  {
    "rank": 52,
    "name": "Roza Theofania Tsoutsika",
    "country": "GRE",
    "points": 21.66
  },
  {
    "rank": 53,
    "name": "Monica Petrut",
    "country": "ROU",
    "points": 21.6
  },
  {
    "rank": 54,
    "name": "Lana Marincel",
    "country": "CRO",
    "points": 21.48
  },
  {
    "rank": 55,
    "name": "Zoë Lemmens",
    "country": "BEL",
    "points": 21.22
  },
  {
    "rank": 56,
    "name": "Anamaria Mikulic",
    "country": "CRO",
    "points": 21.14
  },
  {
    "rank": 57,
    "name": "Lara Filipovic",
    "country": "SRB",
    "points": 19.86
  },
  {
    "rank": 58,
    "name": "Solomiia Savchuk",
    "country": "USA",
    "points": 19.59
  },
  {
    "rank": 59,
    "name": "Alina Lubaseva",
    "country": "ESP",
    "points": 19.01
  },
  {
    "rank": 60,
    "name": "Safia Sevda Askarova",
    "country": "GER",
    "points": 18.61
  },
  {
    "rank": 61,
    "name": "Paula Enrique Caballero",
    "country": "ESP",
    "points": 18.14
  },
  {
    "rank": 62,
    "name": "Skye Taylor",
    "country": "GBR",
    "points": 18.14
  },
  {
    "rank": 63,
    "name": "V Iktoria Varga",
    "country": "CRO",
    "points": 18.0
  },
  {
    "rank": 64,
    "name": "Eileen Santhad",
    "country": "NOR",
    "points": 17.33
  },
  {
    "rank": 65,
    "name": "Alexandra Vasileva",
    "country": "BUL",
    "points": 17.16
  },
  {
    "rank": 66,
    "name": "Asli Cemre Ceylan",
    "country": "TUR",
    "points": 17.01
  },
  {
    "rank": 67,
    "name": "Martina Borras Couraly",
    "country": "ESP",
    "points": 16.98
  },
  {
    "rank": 68,
    "name": "Aleksandra Dimova",
    "country": "BUL",
    "points": 15.47
  },
  {
    "rank": 69,
    "name": "Tova Vilma Kristoffersson",
    "country": "SWE",
    "points": 15.42
  },
  {
    "rank": 70,
    "name": "Neslisah Encok",
    "country": "TUR",
    "points": 15.12
  },
  {
    "rank": 71,
    "name": "Noa Mateo Pelaez",
    "country": "ESP",
    "points": 15.12
  },
  {
    "rank": 72,
    "name": "Elizabeth Adamsons",
    "country": "GBR",
    "points": 15.06
  },
  {
    "rank": 73,
    "name": "Alicia Calvo Rubio",
    "country": "ESP",
    "points": 15.0
  },
  {
    "rank": 74,
    "name": "Peri Hitchen",
    "country": "AUS",
    "points": 14.5
  },
  {
    "rank": 75,
    "name": "Imarah Vizdiklar",
    "country": "KOS",
    "points": 14.45
  },
  {
    "rank": 76,
    "name": "Zoe Martinez Sevilla",
    "country": "ESP",
    "points": 14.32
  },
  {
    "rank": 77,
    "name": "Antonina Cygan",
    "country": "POL",
    "points": 14.04
  },
  {
    "rank": 78,
    "name": "Ayse Sena Diler",
    "country": "TUR",
    "points": 13.68
  },
  {
    "rank": 79,
    "name": "Ioanna Maria Pateraki",
    "country": "GRE",
    "points": 12.96
  },
  {
    "rank": 80,
    "name": "Evangelia Giannopoulou",
    "country": "GRE",
    "points": 12.72
  },
  {
    "rank": 81,
    "name": "Alina Gevorgian",
    "country": "RUS",
    "points": 12.7
  },
  {
    "rank": 82,
    "name": "🇦🇱",
    "country": "ALB",
    "points": 12.7
  },
  {
    "rank": 83,
    "name": "Mia Tamburić",
    "country": "CRO",
    "points": 12.7
  },
  {
    "rank": 84,
    "name": "Diana Hajjari",
    "country": "SWE",
    "points": 12.49
  },
  {
    "rank": 85,
    "name": "Ylenia Baños Arnedo",
    "country": "ESP",
    "points": 12.48
  },
  {
    "rank": 86,
    "name": "Ceren Kucukoglu",
    "country": "TUR",
    "points": 12.27
  },
  {
    "rank": 87,
    "name": "Ivona Turkulj",
    "country": "SRB",
    "points": 12.1
  },
  {
    "rank": 88,
    "name": "Dina Gimenez",
    "country": "FRA",
    "points": 11.88
  },
  {
    "rank": 89,
    "name": "Amela Nuti",
    "country": "MNE",
    "points": 11.84
  },
  {
    "rank": 90,
    "name": "Haya Brousseau--Ma",
    "country": "FRA",
    "points": 11.54
  },
  {
    "rank": 91,
    "name": "Borislava Petkova",
    "country": "BUL",
    "points": 11.12
  },
  {
    "rank": 92,
    "name": "Federica Cipriani",
    "country": "ITA",
    "points": 10.8
  },
  {
    "rank": 93,
    "name": "Lana Meštrović",
    "country": "CRO",
    "points": 10.8
  },
  {
    "rank": 94,
    "name": "Tuana Tuna",
    "country": "TUR",
    "points": 10.8
  },
  {
    "rank": 95,
    "name": "Nehir Saglam",
    "country": "TUR",
    "points": 10.73
  },
  {
    "rank": 96,
    "name": "Anastasiia Filimonova",
    "country": "RUS",
    "points": 10.0
  },
  {
    "rank": 97,
    "name": "🇵🇸",
    "country": "PLE",
    "points": 10.0
  },
  {
    "rank": 98,
    "name": "Eva-Maria Kanalga",
    "country": "SWE",
    "points": 9.96
  },
  {
    "rank": 99,
    "name": "Maelle Zaina Yembi",
    "country": "COD",
    "points": 9.6
  },
  {
    "rank": 100,
    "name": "Zora Réka Kozák",
    "country": "HUN",
    "points": 9.5
  },
  {
    "rank": 101,
    "name": "Erika Lupusor",
    "country": "MDA",
    "points": 9.36
  },
  {
    "rank": 102,
    "name": "Sofia Protonotariou",
    "country": "GRE",
    "points": 9.36
  },
  {
    "rank": 103,
    "name": "Benedetta Muri",
    "country": "ITA",
    "points": 9.06
  },
  {
    "rank": 104,
    "name": "Charikleia Seferi",
    "country": "GRE",
    "points": 9.06
  },
  {
    "rank": 105,
    "name": "Ecrinnisa Altiok",
    "country": "TUR",
    "points": 9.06
  },
  {
    "rank": 106,
    "name": "Elif Hacifazlioglu",
    "country": "TUR",
    "points": 9.06
  },
  {
    "rank": 107,
    "name": "Elif Su Sana",
    "country": "TUR",
    "points": 9.06
  },
  {
    "rank": 108,
    "name": "Erika Russo",
    "country": "ITA",
    "points": 9.06
  },
  {
    "rank": 109,
    "name": "Noemi Malizia",
    "country": "ITA",
    "points": 9.06
  },
  {
    "rank": 110,
    "name": "Shabbon Islambayeva",
    "country": "KAZ",
    "points": 9.02
  },
  {
    "rank": 111,
    "name": "Dora Bračun",
    "country": "CRO",
    "points": 9.0
  },
  {
    "rank": 112,
    "name": "🇮🇹",
    "country": "ITA",
    "points": 9.0
  },
  {
    "rank": 113,
    "name": "Iulia Sandu",
    "country": "MDA",
    "points": 8.89
  },
  {
    "rank": 114,
    "name": "Elena Fazio",
    "country": "ITA",
    "points": 8.59
  },
  {
    "rank": 115,
    "name": "Mariia Papatsenko",
    "country": "UKR",
    "points": 8.42
  },
  {
    "rank": 116,
    "name": "Sara Ruiz Ferruelo",
    "country": "ESP",
    "points": 8.33
  },
  {
    "rank": 117,
    "name": "Alexandra Michailidi",
    "country": "GRE",
    "points": 7.95
  },
  {
    "rank": 118,
    "name": "Lourdes Hrgovic",
    "country": "CRO",
    "points": 7.2
  },
  {
    "rank": 119,
    "name": "Ema De Simone",
    "country": "BEL",
    "points": 6.84
  },
  {
    "rank": 120,
    "name": "Anastasiia Volosenko",
    "country": "UKR",
    "points": 6.62
  },
  {
    "rank": 121,
    "name": "Jimena Sierra Marquez",
    "country": "ESP",
    "points": 6.48
  },
  {
    "rank": 122,
    "name": "Maya Simeonova",
    "country": "BUL",
    "points": 6.48
  },
  {
    "rank": 123,
    "name": "Sofija Hinic",
    "country": "CRO",
    "points": 6.48
  },
  {
    "rank": 124,
    "name": "Anastasia Tsitsi",
    "country": "GRE",
    "points": 6.36
  },
  {
    "rank": 125,
    "name": "Bade Bora",
    "country": "TUR",
    "points": 6.36
  },
  {
    "rank": 126,
    "name": "Beatrice Cirnu",
    "country": "ITA",
    "points": 6.36
  },
  {
    "rank": 127,
    "name": "Birgul Karin Sezis",
    "country": "TUR",
    "points": 6.36
  },
  {
    "rank": 128,
    "name": "Christina Athanasopoulou",
    "country": "GRE",
    "points": 6.36
  },
  {
    "rank": 129,
    "name": "Eleftheria Kalitsi",
    "country": "GRE",
    "points": 6.36
  },
  {
    "rank": 130,
    "name": "Emanuela Nedelcheva",
    "country": "BUL",
    "points": 6.36
  },
  {
    "rank": 131,
    "name": "Kalliopi Kaxira",
    "country": "GRE",
    "points": 6.36
  },
  {
    "rank": 132,
    "name": "Kyriaki Karagkiozaki",
    "country": "GRE",
    "points": 6.36
  },
  {
    "rank": 133,
    "name": "Paraskevi Markidou",
    "country": "CYP",
    "points": 6.36
  },
  {
    "rank": 134,
    "name": "Ana Clara Ribeiro Gonçalves",
    "country": "POR",
    "points": 6.35
  },
  {
    "rank": 135,
    "name": "Lana Jakara",
    "country": "CRO",
    "points": 6.0
  },
  {
    "rank": 136,
    "name": "Ayse Isik",
    "country": "TUR",
    "points": 5.76
  },
  {
    "rank": 137,
    "name": "Sahara-Su Cosgun",
    "country": "GER",
    "points": 5.4
  },
  {
    "rank": 138,
    "name": "Ching Nam Clare Wong",
    "country": "HKG",
    "points": 5.22
  },
  {
    "rank": 139,
    "name": "Stella Kolb",
    "country": "GER",
    "points": 5.11
  },
  {
    "rank": 140,
    "name": "Elsa Leloir",
    "country": "FRA",
    "points": 5.03
  },
  {
    "rank": 141,
    "name": "Beyza Kurucu",
    "country": "TUR",
    "points": 5.0
  },
  {
    "rank": 142,
    "name": "Victoriia Zhybchyn",
    "country": "UKR",
    "points": 4.86
  },
  {
    "rank": 143,
    "name": "Hiranur Teker",
    "country": "TUR",
    "points": 4.66
  },
  {
    "rank": 144,
    "name": "Lucija Stapar",
    "country": "SRB",
    "points": 4.64
  },
  {
    "rank": 145,
    "name": "Ana Maria Georgieva",
    "country": "BUL",
    "points": 4.54
  },
  {
    "rank": 146,
    "name": "Manuela Moreno Clavijo",
    "country": "ESP",
    "points": 4.53
  },
  {
    "rank": 147,
    "name": "Oliwia Andrzejewska",
    "country": "POL",
    "points": 4.53
  },
  {
    "rank": 148,
    "name": "Nadia Mielcarek",
    "country": "POL",
    "points": 4.5
  },
  {
    "rank": 149,
    "name": "Yuliia Lonska",
    "country": "UKR",
    "points": 4.5
  },
  {
    "rank": 150,
    "name": "Patrycja Lubinska",
    "country": "POL",
    "points": 4.43
  },
  {
    "rank": 151,
    "name": "Adriana Avendaño Hernandez",
    "country": "ESP",
    "points": 4.32
  },
  {
    "rank": 152,
    "name": "Ela Kavčič",
    "country": "SLO",
    "points": 4.32
  },
  {
    "rank": 153,
    "name": "Lina Sylva",
    "country": "FRA",
    "points": 4.32
  },
  {
    "rank": 154,
    "name": "Teodora Krstic",
    "country": "SRB",
    "points": 4.32
  },
  {
    "rank": 155,
    "name": "Wiktoria Dzwonnik",
    "country": "POL",
    "points": 3.89
  },
  {
    "rank": 156,
    "name": "Lamise Layla Khan",
    "country": "GBR",
    "points": 3.78
  },
  {
    "rank": 157,
    "name": "Trinity Suh",
    "country": "USA",
    "points": 3.67
  },
  {
    "rank": 158,
    "name": "Ami Sarah Fofana",
    "country": "CIV",
    "points": 3.6
  },
  {
    "rank": 159,
    "name": "Eylul Karadas",
    "country": "TUR",
    "points": 3.6
  },
  {
    "rank": 160,
    "name": "Halo Canezo",
    "country": "USA",
    "points": 3.6
  },
  {
    "rank": 161,
    "name": "Nele Spillner",
    "country": "DEN",
    "points": 3.6
  },
  {
    "rank": 162,
    "name": "Ariana Dorbolo",
    "country": "CRO",
    "points": 3.41
  },
  {
    "rank": 163,
    "name": "Giorgia D'Agostino",
    "country": "ITA",
    "points": 3.41
  },
  {
    "rank": 164,
    "name": "Ayse Bozkurt",
    "country": "TUR",
    "points": 3.33
  },
  {
    "rank": 165,
    "name": "Jazleen Romero",
    "country": "USA",
    "points": 3.29
  },
  {
    "rank": 166,
    "name": "Konstantina Michailidi",
    "country": "GRE",
    "points": 3.24
  },
  {
    "rank": 167,
    "name": "Shams Alizada",
    "country": "AZE",
    "points": 3.24
  },
  {
    "rank": 168,
    "name": "Ecrin Eylul Haliloglu",
    "country": "TUR",
    "points": 3.1
  },
  {
    "rank": 169,
    "name": "Ainara Torrubia Perez",
    "country": "ESP",
    "points": 3.02
  },
  {
    "rank": 170,
    "name": "Chrysanthi Psarrou",
    "country": "GRE",
    "points": 3.02
  },
  {
    "rank": 171,
    "name": "Julija Bukovac",
    "country": "CRO",
    "points": 3.02
  },
  {
    "rank": 172,
    "name": "Maria Koukousoudi",
    "country": "GER",
    "points": 3.02
  },
  {
    "rank": 173,
    "name": "Raya Ivanova",
    "country": "BUL",
    "points": 3.02
  },
  {
    "rank": 174,
    "name": "Tsvety Slavova",
    "country": "BUL",
    "points": 2.92
  },
  {
    "rank": 175,
    "name": "Irene Molina Perez",
    "country": "ESP",
    "points": 2.72
  },
  {
    "rank": 176,
    "name": "Uliana Nikulina",
    "country": "GER",
    "points": 2.59
  },
  {
    "rank": 177,
    "name": "Bahar Hashemi",
    "country": "IRI",
    "points": 2.27
  },
  {
    "rank": 178,
    "name": "Christina Giouvanoudi",
    "country": "GRE",
    "points": 2.27
  },
  {
    "rank": 179,
    "name": "Havva Ilknur Yalcin",
    "country": "TUR",
    "points": 2.27
  },
  {
    "rank": 180,
    "name": "Nisanur Akay",
    "country": "TUR",
    "points": 2.27
  },
  {
    "rank": 181,
    "name": "Vanessa Hallaci",
    "country": "GER",
    "points": 2.27
  },
  {
    "rank": 182,
    "name": "Ceylinnaz Durmaz",
    "country": "TUR",
    "points": 2.19
  },
  {
    "rank": 183,
    "name": "Alexandra Maria Papathanasiou",
    "country": "GER",
    "points": 2.16
  },
  {
    "rank": 184,
    "name": "Bilge Zeynep Mutlu",
    "country": "TUR",
    "points": 2.16
  },
  {
    "rank": 185,
    "name": "Charos Abdullayeva",
    "country": "KAZ",
    "points": 2.16
  },
  {
    "rank": 186,
    "name": "Chrysovalanto Dimitriou",
    "country": "CYP",
    "points": 2.16
  },
  {
    "rank": 187,
    "name": "Eleni Aslanoglou",
    "country": "GRE",
    "points": 2.16
  },
  {
    "rank": 188,
    "name": "Elsa Herber",
    "country": "FRA",
    "points": 2.16
  },
  {
    "rank": 189,
    "name": "Gisela Gutierrez Morros",
    "country": "ESP",
    "points": 2.16
  },
  {
    "rank": 190,
    "name": "Isabel Lindquist",
    "country": "SWE",
    "points": 2.16
  },
  {
    "rank": 191,
    "name": "Jasmin Shire",
    "country": "DEN",
    "points": 2.16
  },
  {
    "rank": 192,
    "name": "Karyna Dovzhanyn",
    "country": "UKR",
    "points": 2.16
  },
  {
    "rank": 193,
    "name": "Melina Georgiadou",
    "country": "GRE",
    "points": 2.16
  },
  {
    "rank": 194,
    "name": "Monica De Simone",
    "country": "BEL",
    "points": 2.16
  },
  {
    "rank": 195,
    "name": "Queenita Keisha Azzahra",
    "country": "INA",
    "points": 2.16
  },
  {
    "rank": 196,
    "name": "Yaren Erdem",
    "country": "TUR",
    "points": 2.16
  },
  {
    "rank": 197,
    "name": "Jana Blecic",
    "country": "CRO",
    "points": 1.8
  },
  {
    "rank": 198,
    "name": "Anna Mahesh",
    "country": "IRL",
    "points": 1.62
  },
  {
    "rank": 199,
    "name": "Danica Sekulic",
    "country": "SRB",
    "points": 1.62
  },
  {
    "rank": 200,
    "name": "Enrieta Berberi",
    "country": "GRE",
    "points": 1.62
  },
  {
    "rank": 201,
    "name": "Lilianna Lubinska",
    "country": "POL",
    "points": 1.62
  },
  {
    "rank": 202,
    "name": "Luisa Prestifilippo",
    "country": "GER",
    "points": 1.62
  },
  {
    "rank": 203,
    "name": "Ula Jarulyte",
    "country": "LTU",
    "points": 1.62
  },
  {
    "rank": 204,
    "name": "Ece Cicek",
    "country": "TUR",
    "points": 1.59
  },
  {
    "rank": 205,
    "name": "Ecrin Elif Ozkum",
    "country": "TUR",
    "points": 1.59
  },
  {
    "rank": 206,
    "name": "Ela Nur Ay",
    "country": "TUR",
    "points": 1.59
  },
  {
    "rank": 207,
    "name": "Estella Pshikhacheva",
    "country": "RUS",
    "points": 1.59
  },
  {
    "rank": 208,
    "name": "Fatma Kilic",
    "country": "TUR",
    "points": 1.59
  },
  {
    "rank": 209,
    "name": "Goknur Kilic",
    "country": "TUR",
    "points": 1.59
  },
  {
    "rank": 210,
    "name": "Gulce Ersoy",
    "country": "TUR",
    "points": 1.59
  },
  {
    "rank": 211,
    "name": "Ipek Serbetci",
    "country": "TUR",
    "points": 1.59
  },
  {
    "rank": 212,
    "name": "Maribel Skaf",
    "country": "LBN",
    "points": 1.59
  },
  {
    "rank": 213,
    "name": "Rana Esilya Kiyi",
    "country": "TUR",
    "points": 1.59
  },
  {
    "rank": 214,
    "name": "Zumra Berber",
    "country": "TUR",
    "points": 1.59
  },
  {
    "rank": 215,
    "name": "Alina Matmanivong",
    "country": "FRA",
    "points": 1.51
  },
  {
    "rank": 216,
    "name": "Ayse-Nur Ayvaz",
    "country": "GER",
    "points": 1.51
  },
  {
    "rank": 217,
    "name": "Berra Demir",
    "country": "TUR",
    "points": 1.51
  },
  {
    "rank": 218,
    "name": "Blanca Ruiz Rosales",
    "country": "ESP",
    "points": 1.51
  },
  {
    "rank": 219,
    "name": "Demetra Andreou",
    "country": "CYP",
    "points": 1.51
  },
  {
    "rank": 220,
    "name": "Ela Su Durmaz",
    "country": "TUR",
    "points": 1.51
  },
  {
    "rank": 221,
    "name": "Elif Nur Erisik",
    "country": "TUR",
    "points": 1.51
  },
  {
    "rank": 222,
    "name": "Emma Rahmoune",
    "country": "FRA",
    "points": 1.51
  },
  {
    "rank": 223,
    "name": "Ezgi Demir",
    "country": "TUR",
    "points": 1.51
  },
  {
    "rank": 224,
    "name": "🇪🇸",
    "country": "ESP",
    "points": 1.51
  },
  {
    "rank": 225,
    "name": "Maja Stryjek",
    "country": "POL",
    "points": 1.51
  },
  {
    "rank": 226,
    "name": "Marharyta Stratiichuk",
    "country": "CZE",
    "points": 1.51
  },
  {
    "rank": 227,
    "name": "Marianna Elizarova",
    "country": "KAZ",
    "points": 1.51
  },
  {
    "rank": 228,
    "name": "Nika Vesanović",
    "country": "CRO",
    "points": 1.51
  },
  {
    "rank": 229,
    "name": "Noelia Juncal Marzoa",
    "country": "ESP",
    "points": 1.51
  },
  {
    "rank": 230,
    "name": "Noemi Scotto D'Aniello",
    "country": "ITA",
    "points": 1.51
  },
  {
    "rank": 231,
    "name": "Rueya Erdem",
    "country": "AUT",
    "points": 1.51
  },
  {
    "rank": 232,
    "name": "Sofiya Ochkalasova",
    "country": "RUS",
    "points": 1.51
  },
  {
    "rank": 233,
    "name": "Sofiya Pakhritdinova",
    "country": "KAZ",
    "points": 1.51
  },
  {
    "rank": 234,
    "name": "Sura Nur Ors",
    "country": "TUR",
    "points": 1.51
  },
  {
    "rank": 235,
    "name": "Vanesa Vrbova",
    "country": "CZE",
    "points": 1.51
  },
  {
    "rank": 236,
    "name": "Zoe Lanz Coria",
    "country": "ESP",
    "points": 1.51
  },
  {
    "rank": 237,
    "name": "Alena Babakova",
    "country": "BLR",
    "points": 1.13
  },
  {
    "rank": 238,
    "name": "Cayla Orribo Andersson",
    "country": "ESP",
    "points": 1.13
  },
  {
    "rank": 239,
    "name": "Chaima Zahraoui",
    "country": "ESP",
    "points": 1.13
  },
  {
    "rank": 240,
    "name": "Eunjung Cho",
    "country": "KOR",
    "points": 1.13
  },
  {
    "rank": 241,
    "name": "Gara Vico Hortalaza",
    "country": "ESP",
    "points": 1.13
  },
  {
    "rank": 242,
    "name": "Kristina Przulj",
    "country": "BIH",
    "points": 1.13
  },
  {
    "rank": 243,
    "name": "Marta Bravo Blanco",
    "country": "ESP",
    "points": 1.13
  },
  {
    "rank": 244,
    "name": "Noelia Pulgarin Muñoz",
    "country": "ESP",
    "points": 1.13
  },
  {
    "rank": 245,
    "name": "Efsa Gul Yilmaz",
    "country": "TUR",
    "points": 1.06
  },
  {
    "rank": 246,
    "name": "Nika Navitskaia",
    "country": "RUS",
    "points": 1.06
  },
  {
    "rank": 247,
    "name": "Sevginas Ak",
    "country": "TUR",
    "points": 1.06
  },
  {
    "rank": 248,
    "name": "Tabasom Moghimi",
    "country": "IRI",
    "points": 1.06
  },
  {
    "rank": 249,
    "name": "Tugsem Alp",
    "country": "TUR",
    "points": 1.06
  },
  {
    "rank": 250,
    "name": "Yusra Suden Yilmaz",
    "country": "TUR",
    "points": 1.06
  },
  {
    "rank": 251,
    "name": "Muriel Llopis Sanchez",
    "country": "ESP",
    "points": 0.76
  }
]